README.md
setup.py
sanic_router/__init__.py
sanic_router/discovery.py
sanic_router/exceptions.py
sanic_router/utils.py
sanic_router.egg-info/PKG-INFO
sanic_router.egg-info/SOURCES.txt
sanic_router.egg-info/dependency_links.txt
sanic_router.egg-info/requires.txt
sanic_router.egg-info/top_level.txt
tests/__init__.py
tests/tests.py
tests/example/__init__.py
tests/example/routes.py
tests/example/views.py
tests/example/schema/__init__.py
tests/example/schema/routes.py
tests/example/schema/views.py